litalign/__about__.py
litalign/__init__.py
litalign/maths/__init__.py
litalign/maths/sum.py
litalign-0.0.3.dist-info/licenses/LICENSE
litalign-0.0.3.dist-info/METADATA
litalign-0.0.3.dist-info/WHEEL
litalign-0.0.3.dist-info/top_level.txt
litalign-0.0.3.dist-info/RECORD
