Metadata-Version: 2.4
Name: litalign
Version: 0.0.3
Summary: Lightning-native library for fine-tuning LLMs using alignment techniques like PPO, DPO, GRPO and more
Home-page: https://github.com/deependujha/litalign
Download-URL: https://github.com/deependujha/litalign
Author: Deependu Jha
Author-email: deependujha21@gmail.com
License: Apache-2.0
Project-URL: Bug Tracker, https://github.com/deependujha/litalign/issues
Project-URL: Documentation, https://github.com/deependujha/litalign/blob/main/README.md
Project-URL: Source Code, https://github.com/deependujha/litalign
Keywords: deep learning,pytorch,AI,streaming,cloud,rlhf,alignment,safety
Classifier: Environment :: Console
Classifier: Natural Language :: English
Classifier: Development Status :: 3 - Alpha
Classifier: Intended Audience :: Developers
Classifier: Topic :: Scientific/Engineering :: Artificial Intelligence
Classifier: Topic :: Scientific/Engineering :: Information Analysis
Classifier: Operating System :: OS Independent
Classifier: Programming Language :: Python :: 3
Classifier: Programming Language :: Python :: 3.8
Classifier: Programming Language :: Python :: 3.9
Classifier: Programming Language :: Python :: 3.10
Classifier: Programming Language :: Python :: 3.11
Classifier: Programming Language :: Python :: 3.12
Requires-Python: >=3.8
License-File: LICENSE
Requires-Dist: torch
Requires-Dist: lightning-utilities
Requires-Dist: numpy
Requires-Dist: requests
Dynamic: author
Dynamic: author-email
Dynamic: classifier
Dynamic: description
Dynamic: description-content-type
Dynamic: download-url
Dynamic: home-page
Dynamic: keywords
Dynamic: license
Dynamic: license-file
Dynamic: project-url
Dynamic: requires-dist
Dynamic: requires-python
Dynamic: summary
